granular_configuration_language/__init__.py
granular_configuration_language/_base_path.py
granular_configuration_language/_build.py
granular_configuration_language/_cache.py
granular_configuration_language/_configuration.py
granular_configuration_language/_json.py
granular_configuration_language/_lazy_load_configuration.py
granular_configuration_language/_locations.py
granular_configuration_language/_merge.py
granular_configuration_language/_mutable_lazy_load_configuration.py
granular_configuration_language/_s.py
granular_configuration_language/_simple_future.py
granular_configuration_language/_utils.py
granular_configuration_language/available_plugins.py
granular_configuration_language/available_tags.py
granular_configuration_language/exceptions.py
granular_configuration_language/proxy/__init__.py
granular_configuration_language/proxy/_proxy.py
granular_configuration_language/py.typed
granular_configuration_language/yaml/__init__.py
granular_configuration_language/yaml/_tags/__init__.py
granular_configuration_language/yaml/_tags/_date.py
granular_configuration_language/yaml/_tags/_del.py
granular_configuration_language/yaml/_tags/_dict.py
granular_configuration_language/yaml/_tags/_eager_parse_file.py
granular_configuration_language/yaml/_tags/_env.py
granular_configuration_language/yaml/_tags/_load_binary.py
granular_configuration_language/yaml/_tags/_mask.py
granular_configuration_language/yaml/_tags/_merge.py
granular_configuration_language/yaml/_tags/_parse_env.py
granular_configuration_language/yaml/_tags/_parse_file.py
granular_configuration_language/yaml/_tags/_placeholder.py
granular_configuration_language/yaml/_tags/_ref.py
granular_configuration_language/yaml/_tags/_sub.py
granular_configuration_language/yaml/_tags/_uuid.py
granular_configuration_language/yaml/_tags/func_and_class.py
granular_configuration_language/yaml/classes.py
granular_configuration_language/yaml/decorators/__init__.py
granular_configuration_language/yaml/decorators/_base.py
granular_configuration_language-2.4.1.dist-info/METADATA
granular_configuration_language-2.4.1.dist-info/WHEEL
granular_configuration_language-2.4.1.dist-info/entry_points.txt
granular_configuration_language-2.4.1.dist-info/licenses/LICENSE
granular_configuration_language-2.4.1.dist-info/RECORD
