Metadata-Version: 2.4
Name: granular-configuration-language
Version: 2.4.1
Summary: This general purpose configuration utility library allows your code to use YAML as a configuration language for internal and external parties, allowing configuration to be crafted from multiple sources and merged just before use, using YAML Tags for additional functionality.
License: MIT
License-File: LICENSE
Author: Eric Jensen
Author-email: eric.jensen42@gmail.com
Requires-Python: >=3.10
Classifier: License :: OSI Approved :: MIT License
Classifier: Natural Language :: English
Classifier: Operating System :: OS Independent
Classifier: Programming Language :: Python :: 3
Classifier: Programming Language :: Python :: 3.10
Classifier: Programming Language :: Python :: 3.11
Classifier: Programming Language :: Python :: 3.12
Classifier: Programming Language :: Python :: 3.13
Classifier: Programming Language :: Python :: 3.14
Classifier: Topic :: Utilities
Classifier: Typing :: Typed
Provides-Extra: printing
Requires-Dist: python-dateutil ; python_version < "3.11"
Requires-Dist: python-jsonpath
Requires-Dist: ruamel.yaml (>=0.18)
Requires-Dist: tabulate (>=0.9.0) ; extra == "printing"
Project-URL: Documentation, https://lifedox.github.io/granular-configuration-language/README.html
Project-URL: Homepage, https://lifedox.github.io/granular-configuration-language/README.html
Project-URL: Repository, https://github.com/lifedox/granular-configuration-language
